{
  "shopUID": 2,
  "shopName": "Grace's Graceful Clothing",
  "currency": "MARK_OF_GRACE",
  "sellPolicy": "STOCK_ONLY",
  "items": [
    {
      "id": 11851,
      "amount": 100,
      "sellPrice": 11,
      "buyPrice": 14
    },
    {
      "id": 11853,
      "amount": 100,
      "sellPrice": 12,
      "buyPrice": 16
    },
    {
      "id": 11855,
      "amount": 100,
      "sellPrice": 17,
      "buyPrice": 22
    },
    {
      "id": 11857,
      "amount": 100,
      "sellPrice": 19,
      "buyPrice": 24
    },
    {
      "id": 11859,
      "amount": 100,
      "sellPrice": 9,
      "buyPrice": 12
    },
    {
      "id": 11861,
      "amount": 100,
      "sellPrice": 12,
      "buyPrice": 16
    },
    {
      "id": 12641,
      "amount": 1000,
      "sellPrice": 1,
      "buyPrice": 4
    }
  ]
}
